tilburg_hand/__init__.py
tilburg_hand/motor_interface.py
tilburg_hand/motorgui/__init__.py
tilburg_hand/motorgui/config.json
tilburg_hand/motorgui/motor_gui.py
tilburg_hand-1.1.0.dist-info/licenses/LICENSE
tilburg_hand_urdf_mujoco/cable_routing_proximal.part
tilburg_hand_urdf_mujoco/cable_routing_proximal.stl
tilburg_hand_urdf_mujoco/config.json
tilburg_hand_urdf_mujoco/distal_finalshape.part
tilburg_hand_urdf_mujoco/distal_finalshape.stl
tilburg_hand_urdf_mujoco/distal_finalshape_2_collision.stl
tilburg_hand_urdf_mujoco/distal_finalshape_2_visual.stl
tilburg_hand_urdf_mujoco/distal_finalshape_3_collision.stl
tilburg_hand_urdf_mujoco/distal_finalshape_3_visual.stl
tilburg_hand_urdf_mujoco/distal_finalshape_collision.stl
tilburg_hand_urdf_mujoco/distal_finalshape_visual.stl
tilburg_hand_urdf_mujoco/handbase_and_motors_collision.stl
tilburg_hand_urdf_mujoco/handbase_and_motors_visual.stl
tilburg_hand_urdf_mujoco/mcp_3.part
tilburg_hand_urdf_mujoco/mcp_3.stl
tilburg_hand_urdf_mujoco/mcp_3_2_collision.stl
tilburg_hand_urdf_mujoco/mcp_3_2_visual.stl
tilburg_hand_urdf_mujoco/mcp_3_3_collision.stl
tilburg_hand_urdf_mujoco/mcp_3_3_visual.stl
tilburg_hand_urdf_mujoco/mcp_3_collision.stl
tilburg_hand_urdf_mujoco/mcp_3_visual.stl
tilburg_hand_urdf_mujoco/middle_phalange_2_collision.stl
tilburg_hand_urdf_mujoco/middle_phalange_2_visual.stl
tilburg_hand_urdf_mujoco/middle_phalange_3_collision.stl
tilburg_hand_urdf_mujoco/middle_phalange_3_visual.stl
tilburg_hand_urdf_mujoco/middle_phalange_collision.stl
tilburg_hand_urdf_mujoco/middle_phalange_visual.stl
tilburg_hand_urdf_mujoco/middle_phalanx.part
tilburg_hand_urdf_mujoco/middle_phalanx.stl
tilburg_hand_urdf_mujoco/part_1.part
tilburg_hand_urdf_mujoco/part_1.stl
tilburg_hand_urdf_mujoco/proximal_phalange_2_collision.stl
tilburg_hand_urdf_mujoco/proximal_phalange_2_visual.stl
tilburg_hand_urdf_mujoco/proximal_phalange_3_collision.stl
tilburg_hand_urdf_mujoco/proximal_phalange_3_visual.stl
tilburg_hand_urdf_mujoco/proximal_phalange_4_collision.stl
tilburg_hand-1.1.0.dist-info/METADATA
tilburg_hand-1.1.0.dist-info/WHEEL
tilburg_hand-1.1.0.dist-info/entry_points.txt
tilburg_hand-1.1.0.dist-info/top_level.txt
tilburg_hand-1.1.0.dist-info/RECORD
