Metadata-Version: 2.4
Name: tilburg_hand
Version: 1.1.0
Summary: Tilburg Hand motor interface and example code.
Author-email: Giacomo Spigler <contact@tilburg-robotics.eu>
License: MIT License
Project-URL: Homepage, https://www.tilburg-robotics.eu
Project-URL: GitHub, https://github.com/TilburgRobotics
Keywords: Tilburg Hand,robot hand,robotics,low-cost dexterous robot hand
Classifier: Programming Language :: Python :: 3
Classifier: License :: OSI Approved :: MIT License
Classifier: Operating System :: OS Independent
Requires-Python: >=3.7
License-File: LICENSE
Requires-Dist: pyserial>=3.5
Requires-Dist: dynamixel-sdk>=3.7
Dynamic: license-file
